beat_craft_sdk/__init__.py
beat_craft_sdk/config.py
beat_craft_sdk/core.py
beat_craft_sdk/craft_strategy.py
beat_craft_sdk/crafting_with_backingtrack.py
beat_craft_sdk/crafting_with_genetic.py
beat_craft_sdk/transformer.py
beat_craft_sdk/algorithms/__init__.py
beat_craft_sdk/algorithms/genetic.py
beat_craft_sdk/algorithms/melody_genetic.py
beat_craft_sdk/algorithms/phrase_generator_backtracking.py
beat_craft_sdk/algorithms/phrase_generator_genetic.py
beat_craft_sdk/algorithms/player.py
beat_craft_sdk/algorithms/scale_generator.py
beat_craft_sdk/evaluation/__init__.py
beat_craft_sdk/evaluation/beat_craft_evaluation.py
beat_craft_sdk/utils/__init__.py
beat_craft_sdk/utils/audio_converter.py
beat_craft_sdk/utils/beat_craft_utils.py
beatcraft-1.1.5.dist-info/METADATA
beatcraft-1.1.5.dist-info/WHEEL
beatcraft-1.1.5.dist-info/top_level.txt
beatcraft-1.1.5.dist-info/RECORD
